README.txt
pivideo.py
pivideo_class.py
setup.cfg
setup.py
pivideo.egg-info/PKG-INFO
pivideo.egg-info/SOURCES.txt
pivideo.egg-info/dependency_links.txt
pivideo.egg-info/entry_points.txt
pivideo.egg-info/requires.txt
pivideo.egg-info/top_level.txt