Metadata-Version: 1.1
Name: pivideo
Version: 0.1.13
Summary: Raspberry Pi PiVideo Utilities for PiCapture
Home-page: http://lintestsystems.com/
Author: Lintest Systems LLC
Author-email: contact@lintestsystems.com
License: MIT
Keywords: PiCapture Raspberry Pi Video
Platform: UNKNOWN
Classifier: Development Status :: 5 - Production/Stable
Classifier: License :: OSI Approved :: MIT License
Classifier: Programming Language :: Python :: 2
Classifier: Programming Language :: Python :: 2.6
Classifier: Programming Language :: Python :: 2.7
Classifier: Programming Language :: Python :: 3
Classifier: Programming Language :: Python :: 3.2
Classifier: Programming Language :: Python :: 3.3
Classifier: Programming Language :: Python :: 3.4
